[
  {
    "rank": 1,
    "title": "Bokeh",
    "artist": "ぽんぽこ",
    "plays": 449,
    "size": "large",
    "spotify_url": "https://open.spotify.com/track/6TVWpReh64k1IbMDJOjvLQ",
    "image_url": "https://i.scdn.co/image/ab67616d0000b273290d41ec47fe63f9a0bb741d"
  },
  {
    "rank": 2,
    "title": "斜陽",
    "artist": "ヨルシカ",
    "plays": 163,
    "size": "large",
    "spotify_url": "https://open.spotify.com/track/2U6mFmBDjaAu6oCCDRpRet",
    "image_url": "https://i.scdn.co/image/ab67616d0000b273ff8170ccbc49ad0cc9c00b15"
  },
  {
    "rank": 3,
    "title": "火星人",
    "artist": "ヨルシカ",
    "plays": 97,
    "size": "medium",
    "spotify_url": "https://open.spotify.com/track/5RKDnMLQdvkk4OLxF0uBj6",
    "image_url": "https://i.scdn.co/image/ab67616d0000b273bf6d9ce80cf22dbba24efdbb"
  },
  {
    "rank": 4,
    "title": "CHILDAYS",
    "artist": "BLOOM VASE",
    "plays": 76,
    "size": "medium",
    "spotify_url": "https://open.spotify.com/track/1g1AXdio16Yh5SXgPBXcfq",
    "image_url": "https://i.scdn.co/image/ab67616d0000b273eaf3ad9824c6a965dc7bccb6"
  },
  {
    "rank": 5,
    "title": "夜行",
    "artist": "ヨルシカ",
    "plays": 70,
    "size": "medium",
    "spotify_url": "https://open.spotify.com/track/1sPu1euMR0UlTMFFWHh4wB",
    "image_url": "https://i.scdn.co/image/ab67616d0000b2732475099390ec5e6487256925"
  },
  {
    "rank": 6,
    "title": "TIME TO LUV (feat. 幾田りら)",
    "artist": "ピーナッツくん",
    "plays": 57,
    "size": "small",
    "spotify_url": "https://open.spotify.com/track/2rQAvl1XSb28FVq7eL2Z2j",
    "image_url": "https://i.scdn.co/image/ab67616d0000b2734873c0e0aab477bb38c07886"
  },
  {
    "rank": 7,
    "title": "weekly",
    "artist": "にしな",
    "plays": 53,
    "size": "small",
    "spotify_url": "https://open.spotify.com/track/6DeyonC0kWc9WmHo5PilOA",
    "image_url": "https://i.scdn.co/image/ab67616d0000b27372730d2805899829fb3d1cac"
  },
  {
    "rank": 8,
    "title": "Chocolate",
    "artist": "CHANMINA",
    "plays": 40,
    "size": "small",
    "spotify_url": "https://open.spotify.com/track/6CU3VvoeQgkg4Wb1vS0zj7",
    "image_url": "https://i.scdn.co/image/ab67616d0000b2737f485f8a4f640ff53611be0e"
  },
  {
    "rank": 9,
    "title": "プレイシック",
    "artist": "ヨルシカ",
    "plays": 38,
    "size": "small",
    "spotify_url": "https://open.spotify.com/track/4HWJSaMneOtNkFOrD1LU0c",
    "image_url": "https://i.scdn.co/image/ab67616d0000b27341bbd3feddbe89025c3d4fd2"
  },
  {
    "rank": 10,
    "title": "Something Comforting",
    "artist": "Porter Robinson",
    "plays": 37,
    "size": "small",
    "spotify_url": "https://open.spotify.com/track/0AGCxjgxUcTfEhRwCwQdQ3",
    "image_url": "https://i.scdn.co/image/ab67616d0000b273a6de55fe4c950e6e4910f781"
  },
  {
    "rank": 11,
    "title": "アストロビート",
    "artist": "Dannie May",
    "plays": 32,
    "size": "small",
    "spotify_url": "https://open.spotify.com/track/0gwXJLBIchAOXF6JH29RmC",
    "image_url": "https://i.scdn.co/image/ab67616d0000b2736598d621bcc2485d8178784d"
  },
  {
    "rank": 12,
    "title": "ワールドイズマイン - かぐや&月見ヤチヨ ver. - CPK! Remix",
    "artist": "ryo (supercell)",
    "plays": 30,
    "size": "small",
    "spotify_url": "https://open.spotify.com/track/0LswwmDZ6Qk26ZgVRf7aMO",
    "image_url": "https://i.scdn.co/image/ab67616d0000b273c688d674ffa87ec3e13810f3"
  },
  {
    "rank": 13,
    "title": "茜",
    "artist": "ヨルシカ",
    "plays": 25,
    "size": "small",
    "spotify_url": "https://open.spotify.com/track/2TSJ1d6cLgHqrrCIRN3bn2",
    "image_url": "https://i.scdn.co/image/ab67616d0000b273da956a7a9ece3e30ef741490"
  },
  {
    "rank": 14,
    "title": "DUET",
    "artist": "ZICO",
    "plays": 22,
    "size": "small",
    "spotify_url": "https://open.spotify.com/track/0M4O6UEu4F9SxImTsBuX9n",
    "image_url": "https://i.scdn.co/image/ab67616d0000b27376b859d6874da8750df6608a"
  },
  {
    "rank": 15,
    "title": "nevermind",
    "artist": "muque",
    "plays": 18,
    "size": "small",
    "spotify_url": "https://open.spotify.com/track/0CRbc6n3eHpJNr5Xy97IX1",
    "image_url": "https://i.scdn.co/image/ab67616d0000b2730eaf86b247136eb13c1977a6"
  },
  {
    "rank": 16,
    "title": "フィナーレ。",
    "artist": "eill",
    "plays": 17,
    "size": "small",
    "spotify_url": "https://open.spotify.com/track/5qIlqZyWVeQeQ7weYYvrKv",
    "image_url": "https://i.scdn.co/image/ab67616d0000b273c6b96eab2bb1fa0b1b606fb0"
  },
  {
    "rank": 17,
    "title": "逃亡",
    "artist": "ヨルシカ",
    "plays": 16,
    "size": "small",
    "spotify_url": "https://open.spotify.com/track/444TdAemfLOz77t9dlCeAa",
    "image_url": "https://i.scdn.co/image/ab67616d0000b2732794743c6eb13addc2b01420"
  },
  {
    "rank": 18,
    "title": "サラダボウル",
    "artist": "Aooo",
    "plays": 16,
    "size": "small",
    "spotify_url": "https://open.spotify.com/track/4QHnIlkaPHu6vC0EbeLwtk",
    "image_url": "https://i.scdn.co/image/ab67616d0000b273a1f406cb1534c1d1f4c79cb2"
  },
  {
    "rank": 19,
    "title": "此岸",
    "artist": "wata",
    "plays": 15,
    "size": "small",
    "spotify_url": "https://open.spotify.com/track/1pynepGxUThXpxE349VEKX",
    "image_url": "https://i.scdn.co/image/ab67616d0000b273fdca5ba9108c06d212225b28"
  },
  {
    "rank": 20,
    "title": "小波",
    "artist": "wata",
    "plays": 15,
    "size": "small",
    "spotify_url": "https://open.spotify.com/track/3RXeOxX6iSOPuGuvlBOeQD",
    "image_url": "https://i.scdn.co/image/ab67616d0000b273fdca5ba9108c06d212225b28"
  }
]